Workbook

Sheet Premissas
A1: Oraklo · Premissas de custo por cliente
A2: Edite só as células em azul. Fundo amarelo = premissa que mais mexe no resultado. Valores em preto são fórmulas.
A4: Geral
A5: Câmbio (R$ por US$) | B5: 5.5 | F5: Ajuste para a cotação do dia (não encontrei cotação confiável na pesquisa).
A6: Taxas sobre a receita (gateway de pagamento + impostos) | B6: 0.1 | F6: Estimativa: ~4% de gateway + ~6% de Simples Nacional. Confirme com o contador.
A7: Clientes pagantes (para ratear a infra fixa) | B7: 20
A9: Preço dos pacotes (R$) — lib/pacotes.ts
A10: Free (por mês) | B10: 0
A11: Premium (por mês) | B11: 109.99
A12: Premium 3 meses (preço do trimestre) | B12: 299.99
A13: Ultra (por mês) | B13: 599
A15: Claude (IA) — US$ por milhão de tokens
A16: Modelo | B16: Entrada | C16: Saída | F16: Fonte
A17: Opus 5.5 | B17: 4 | C17: 20 | F17: Preços oficiais da Anthropic (tabela de 06/10/2026).
A18: Sonnet 5.5 | B18: 2 | C18: 10
A19: Haiku 5.5 | B19: 0.1 | C19: 0.5
A20: Modelo em uso no código (lib/ia.ts usa Opus 5.5) | B20: Opus 5.5
A21: Tokens de entrada por texto (prompt do sistema + pedido) | B21: 700
A22: Tokens de saída por texto (texto + raciocínio, effort low) | B22: 600
A23: Custo por texto com o modelo em uso (US$) | B23: =(B21*INDEX(B17:B19,MATCH(B20,A17:A19,0))+B22*INDEX(C17:C19,MATCH(B20,A17:A19,0)))/1000000
A24: Custo por texto se trocar para Haiku 5.5 (US$) | B24: =(B21*B19+B22*C19)/1000000
A26: Resend (e-mail)
A27: Preço do plano Pro (US$/mês) | B27: 20 | F27: Pro US$ 20 / 50 mil e-mails; excedente ~US$ 0,90 por mil. Política de uso proíbe e-mail frio.
A28: E-mails inclusos no plano | B28: 50000
A29: Custo por e-mail (US$) | B29: =B27/B28
A30: Envios por e-mail do limite quando há follow-up | B30: 2
A32: Hunter (decisores)
A33: Preço do plano Starter (US$/mês) | B33: 49 | F33: Starter US$ 49 mensal (US$ 34 no anual) / 2.000 créditos. Créditos não acumulam.
A34: Créditos inclusos | B34: 2000
A35: Custo por crédito (US$) | B35: =B33/B34
A36: E-mails encontrados por busca (1 crédito cada; a busca pede até 10) | B36: 5
A38: Uso por cliente
A39: Premissa | B39: Free | C39: Premium | D39: Premium 3 meses | E39: Ultra | F39: Observação
A40: Uso do limite de e-mails e IA (%) | B40: 1 | C40: 1 | D40: 1 | E40: 1 | F40: 100% = pior caso (cliente usa tudo). Reduza para o uso médio esperado.
A41: Buscas de decisores por mês | B41: 0 | C41: 100 | D41: 100 | E41: 300 | F41: Não há limite no código para Premium/Ultra: este número é só uma premissa.

Sheet Infra fixa
A1: Infra fixa mensal (independe do número de clientes)
A2: As APIs pagas por uso (Claude, Resend, Hunter) entram por cliente na aba Custo por cliente, pelo custo unitário.
A4: Item | B4: US$/mês | C4: R$/mês | D4: Observação
A5: Vercel Pro (2 assentos de deploy) | B5: 40 | C5: =B5*Premissas!$B$5 | D5: Hobby (grátis) não permite uso comercial. Pro: US$ 20 com 1 assento + US$ 20 de crédito de uso.
A6: Supabase Pro | B6: 25 | C6: =B6*Premissas!$B$5 | D6: Inclui ~8 GB de banco e 1 instância Micro. Base sob demanda cabe por bastante tempo.
A7: Worker da importação (VPS / Railway / Fly) | B7: 10 | C7: =B7*Premissas!$B$5 | D7: Estimativa. Processo contínuo com ~20 GB de disco para os arquivos da Receita.
A8: Domínio (.com.br, ~R$ 40/ano) | C8: 3.3333333 | D8: Valor em reais, rateado por mês.
A9: Total | B9: =SUM(B5:B8) | C9: =SUM(C5:C8)
A11: Infra por cliente pagante (R$/mês) | C11: =IFERROR(C9/Premissas!B7,0)
A12: Clientes Premium para pagar a infra (ponto de equilíbrio) | C12: =IFERROR(ROUNDUP(C9/'Custo por cliente'!C20,0),"-") | D12: Infra total ÷ margem do Premium antes da infra.

Sheet Custo por cliente
A1: Custo e margem por cliente, por mês (R$)
A2: Tudo calculado a partir da aba Premissas. Limites copiados de lib/pacotes.ts.
B4: Free | C4: Premium | D4: Premium 3 meses | E4: Ultra | F4: Como é calculado
A5: Receita
A6: Preço por mês | B6: =Premissas!B10 | C6: =Premissas!B11 | D6: =Premissas!B12/3 | E6: =Premissas!B13 | F6: Premium 3 meses = preço do trimestre ÷ 3.
A7: Receita líquida (após taxas) | B7: =B6*(1-Premissas!$B$6) | C7: =C6*(1-Premissas!$B$6) | D7: =D6*(1-Premissas!$B$6) | E7: =E6*(1-Premissas!$B$6)
A8: Limites do pacote (lib/pacotes.ts)
A9: E-mails por mês (primeiro envio) | B9: 20 | C9: 1000 | D9: 1000 | E9: 5000
A10: Follow-up automático (1 = sim) | B10: 0 | C10: 1 | D10: 1 | E10: 1
A11: Textos com IA por mês | B11: 10 | C11: 200 | D11: 200 | E11: 1000
A12: Uso considerado
A13: E-mails enviados (inclui follow-up) | B13: =B9*Premissas!B40*IF(B10=1,Premissas!$B$30,1) | C13: =C9*Premissas!C40*IF(C10=1,Premissas!$B$30,1) | D13: =D9*Premissas!D40*IF(D10=1,Premissas!$B$30,1) | E13: =E9*Premissas!E40*IF(E10=1,Premissas!$B$30,1) | F13: Limite × % de uso × 2 quando há follow-up.
A14: Textos gerados com IA | B14: =B11*Premissas!B40 | C14: =C11*Premissas!C40 | D14: =D11*Premissas!D40 | E14: =E11*Premissas!E40
A15: Buscas de decisores (Hunter) | B15: =Premissas!B41 | C15: =Premissas!C41 | D15: =Premissas!D41 | E15: =Premissas!E41
A16: Custos variáveis (R$/mês)
A17: IA (Claude, modelo em uso) | B17: =B14*Premissas!$B$23*Premissas!$B$5 | C17: =C14*Premissas!$B$23*Premissas!$B$5 | D17: =D14*Premissas!$B$23*Premissas!$B$5 | E17: =E14*Premissas!$B$23*Premissas!$B$5
A18: E-mail (Resend) | B18: =B13*Premissas!$B$29*Premissas!$B$5 | C18: =C13*Premissas!$B$29*Premissas!$B$5 | D18: =D13*Premissas!$B$29*Premissas!$B$5 | E18: =E13*Premissas!$B$29*Premissas!$B$5
A19: Decisores (Hunter) | B19: =B15*Premissas!$B$36*Premissas!$B$35*Premissas!$B$5 | C19: =C15*Premissas!$B$36*Premissas!$B$35*Premissas!$B$5 | D19: =D15*Premissas!$B$36*Premissas!$B$35*Premissas!$B$5 | E19: =E15*Premissas!$B$36*Premissas!$B$35*Premissas!$B$5
A20: Margem antes da infra | B20: =B7-SUM(B17:B19) | C20: =C7-SUM(C17:C19) | D20: =D7-SUM(D17:D19) | E20: =E7-SUM(E17:E19)
A21: Resultado
A22: Infra fixa rateada | B22: 0 | C22: ='Infra fixa'!$C$11 | D22: ='Infra fixa'!$C$11 | E22: ='Infra fixa'!$C$11 | F22: Free não recebe rateio: o custo dele aparece como margem negativa.
A23: Custo total por cliente | B23: =SUM(B17:B19)+B22 | C23: =SUM(C17:C19)+C22 | D23: =SUM(D17:D19)+D22 | E23: =SUM(E17:E19)+E22
A24: Margem por cliente | B24: =B7-B23 | C24: =C7-C23 | D24: =D7-D23 | E24: =E7-E23
A25: Margem sobre a receita líquida | B25: =IF(B7=0,"-",B24/B7) | C25: =IF(C7=0,"-",C24/C7) | D25: =IF(D7=0,"-",D24/D7) | E25: =IF(E7=0,"-",E24/E7)
A27: Simulação: IA com Haiku 5.5
A28: Custo de IA com Haiku 5.5 | B28: =B14*Premissas!$B$24*Premissas!$B$5 | C28: =C14*Premissas!$B$24*Premissas!$B$5 | D28: =D14*Premissas!$B$24*Premissas!$B$5 | E28: =E14*Premissas!$B$24*Premissas!$B$5
A29: Economia por cliente | B29: =B17-B28 | C29: =C17-C28 | D29: =D17-D28 | E29: =E17-E28
A30: Margem por cliente com Haiku 5.5 | B30: =B24+B29 | C30: =C24+C29 | D30: =D24+D29 | E30: =E24+E29 | F30: Só faz sentido se a qualidade dos textos se mantiver: teste antes de trocar.
A32: Teto do Hunter: decisores por mês que zeram a margem
A33: Buscas de decisores até a margem chegar a zero | B33: - | C33: =IFERROR(MAX(0,ROUNDDOWN((C24+C19)/(Premissas!$B$36*Premissas!$B$35*Premissas!$B$5),0)),"-") | D33: =IFERROR(MAX(0,ROUNDDOWN((D24+D19)/(Premissas!$B$36*Premissas!$B$35*Premissas!$B$5),0)),"-") | E33: =IFERROR(MAX(0,ROUNDDOWN((E24+E19)/(Premissas!$B$36*Premissas!$B$35*Premissas!$B$5),0)),"-") | F33: Base para definir um limite mensal de decisores por pacote (hoje não existe).

Sheet Notas e fontes
A1: Riscos encontrados no código e fontes dos preços
A3: RISCOS NO CÓDIGO
A4: Decisores sem limite | B4: app/(app)/leads/enriquecer.ts só verifica se o pacote libera decisores; não conta buscas. Cada busca pede até 10 e-mails ao Hunter (1 crédito cada), na conta da Oraklo. É o custo variável com maior risco.
A5: Follow-up fora do limite | B5: lib/planos.ts conta só o primeiro e-mail (step 1). Com follow-up, os envios reais chegam a 2× o limite do pacote.
A6: IA no modelo mais caro | B6: lib/ia.ts usa claude-opus-5-5 (US$ 4 / US$ 20 por milhão de tokens). O Haiku 5.5 custa US$ 0,10 / US$ 0,50, cerca de 40× menos.
A7: Vercel Hobby | B7: O plano grátis da Vercel não permite uso comercial. Para vender assinatura é preciso o Pro.
A8: Resend e e-mail frio | B8: A política de uso da Resend proíbe envio para listas que não pediram para receber. O risco é bloqueio da conta, não custo.
A10: FONTES DOS PREÇOS | B10: Pesquisa feita em 24/10/2026. Confira nas páginas oficiais antes de fechar preços.
A11: Claude (Anthropic) | B11: Tabela oficial de preços por modelo (atualizada em 06/10/2026): https://platform.claude.com/docs/en/about-claude/pricing
A12: Hunter | B12: https://hunter.io/pricing · resumo: https://www.saleshandy.com/blog/hunter-io-pricing/
A13: Resend | B13: https://resend.com/pricing · resumo: https://www.usecarly.com/blog/resend-pricing/
A14: Supabase | B14: https://supabase.com/pricing · resumo: https://makerkit.dev/blog/md/saas/supabase-pricing
A15: Vercel | B15: https://vercel.com/docs/plans/pro · https://makerkit.dev/blog/saas/vercel-cost
A16: Câmbio | B16: Não encontrei cotação confiável na pesquisa: ajuste Premissas!B5.
A17: Limites e preços dos pacotes | B17: lib/pacotes.ts (LIMITES e PACOTES), versão da main em 24/10/2026.
